pyme/PymeImage.py
pyme/__init__.py
pyme/impact.ttf
pyme_pillow-0.1.1.dist-info/WHEEL
pyme_pillow-0.1.1.dist-info/METADATA
pyme_pillow-0.1.1.dist-info/RECORD
